student_utils/__init__.py
student_utils/math_utils.py
student_utils/string_utils.py
student_utils_fatima-0.1.0.dist-info/METADATA
student_utils_fatima-0.1.0.dist-info/WHEEL
student_utils_fatima-0.1.0.dist-info/top_level.txt
student_utils_fatima-0.1.0.dist-info/RECORD
