Metadata-Version: 2.4
Name: student-utils-fatima
Version: 0.1.0
Summary: A simple utility library for students
Author: Fatima Arshad
Author-email: s2024332013@umt.edu.pk
Requires-Python: >=3.7
Dynamic: author
Dynamic: author-email
Dynamic: requires-python
Dynamic: summary
